cloco_cli/__init__.py
cloco_cli/cli.py
cloco_cli-0.1.7.dist-info/DESCRIPTION.rst
cloco_cli-0.1.7.dist-info/METADATA
cloco_cli-0.1.7.dist-info/RECORD
cloco_cli-0.1.7.dist-info/WHEEL
cloco_cli-0.1.7.dist-info/entry_points.txt
cloco_cli-0.1.7.dist-info/metadata.json
cloco_cli-0.1.7.dist-info/top_level.txt
