Metadata-Version: 2.0
Name: cloco-cli
Version: 0.1.7
Summary: A command line interface for the cloco API.
Home-page: https://github.com/cloudconfig/cloco-cli
Author: 345 Systems
Author-email: info@345.systems
License: BSD
Download-URL: https://github.com/cloudconfig/cloco-cli/tarball/0.1.7
Keywords: cloco,cloudconfig,configuration,configuration-as-a-service,devops
Platform: any
Classifier: Development Status :: 4 - Beta
Classifier: Environment :: Console
Classifier: Intended Audience :: Developers
Classifier: Intended Audience :: Information Technology
Classifier: Intended Audience :: System Administrators
Classifier: License :: OSI Approved :: MIT License
Classifier: Natural Language :: English
Classifier: Operating System :: POSIX
Classifier: Operating System :: MacOS
Classifier: Operating System :: Unix
Classifier: Operating System :: Microsoft :: Windows
Classifier: Programming Language :: Python
Classifier: Programming Language :: Python :: 2
Classifier: Programming Language :: Python :: 3
Classifier: Topic :: Software Development :: Libraries :: Python Modules
Classifier: Topic :: Software Development :: Build Tools
Requires-Dist: click
Requires-Dist: configparser
Requires-Dist: requests
